disentangle/__init__.py
disentangle/__main__.py
disentangle/array.py
disentangle/cli.py
disentangle/dataset.py
disentangle/image.py
disentangle/loss.py
disentangle/visualize.py
disentangle/architectures/__init__.py
disentangle/architectures/architecture_params.py
disentangle/architectures/base.py
disentangle/architectures/block.py
disentangle/architectures/decoder.py
disentangle/architectures/encoder.py
disentangle/architectures/network.py
disentangle/architectures/test_functions.py
disentangle/architectures/vae.py
disentangle/general/__init__.py
disentangle/general/constants.py
disentangle/general/tools.py
disentangle/other_library_tools/__init__.py
disentangle/other_library_tools/disentanglementlib_tools.py
disentangle-0.0.5.dist-info/AUTHORS.rst
disentangle-0.0.5.dist-info/LICENSE
disentangle-0.0.5.dist-info/METADATA
disentangle-0.0.5.dist-info/WHEEL
disentangle-0.0.5.dist-info/entry_points.txt
disentangle-0.0.5.dist-info/top_level.txt
disentangle-0.0.5.dist-info/RECORD
