Metadata-Version: 2.1
Name: disentangle
Version: 0.0.5
Summary: Quickly create disentanglement pipelines for machine learning research.
Home-page: https://github.com/yukunchen113/disentangle
Author: Yukun Chen
Author-email: yukunchenlib@gmail.com
License: MIT
Project-URL: Documentation, https://disentangle.readthedocs.io/
Project-URL: Changelog, https://disentangle.readthedocs.io/en/latest/changelog.html
Project-URL: Issue Tracker, https://github.com/yukunchen113/disentangle/issues
Platform: UNKNOWN
Classifier: Development Status :: 5 - Production/Stable
Classifier: Intended Audience :: Developers
Classifier: License :: OSI Approved :: MIT License
Classifier: Operating System :: Unix
Classifier: Operating System :: POSIX
Classifier: Programming Language :: Python
Classifier: Programming Language :: Python :: 3.6
Classifier: Programming Language :: Python :: 3.7
Classifier: Programming Language :: Python :: 3.8
Classifier: Programming Language :: Python :: Implementation :: CPython
Classifier: Programming Language :: Python :: Implementation :: PyPy
Classifier: Topic :: Utilities
Requires-Python: >=3.6, !=3.0.*, !=3.1.*, !=3.2.*, !=3.3.*, !=3.4.*
Requires-Dist: opencv-python (>=4.2.0.32)
Requires-Dist: h5py (>=2.10.0)
Requires-Dist: numpy (>=1.13.3)
Requires-Dist: imageio (>=2.6.1)
Provides-Extra: tf
Requires-Dist: tensorflow (>=2.1.0) ; extra == 'tf'
Provides-Extra: tf_gpu
Requires-Dist: tensorflow-gpu (>=2.1.0) ; extra == 'tf_gpu'
